CABS/__init__.py
CABS/__main__.py
CABS/align.py
CABS/atom.py
CABS/ca2all.py
CABS/cabs.py
CABS/cluster.py
CABS/cmap.py
CABS/filter.py
CABS/job.py
CABS/logger.py
CABS/optparser.py
CABS/pdblib.py
CABS/plots.py
CABS/protein.py
CABS/restraints.py
CABS/trajectory.py
CABS/utils.py
CABS/vector3d.py
CABS/data/data0.dat
CABS/data/data1.dat
CABS/data/data2.dat
cabs-0.9.14.dist-info/DESCRIPTION.rst
cabs-0.9.14.dist-info/METADATA
cabs-0.9.14.dist-info/RECORD
cabs-0.9.14.dist-info/WHEEL
cabs-0.9.14.dist-info/entry_points.txt
cabs-0.9.14.dist-info/metadata.json
cabs-0.9.14.dist-info/top_level.txt
