Metadata-Version: 2.0
Name: cabs
Version: 0.9.14
Summary: CABS in python
Home-page: https://bitbucket.org/lcbio/cabsdock
Author: Laboratory of Computational Biology
Author-email: mkurc@cnbc.uw.edu.pl
License: MIT
Platform: UNKNOWN
Requires-Dist: matplotlib (>=2.0)
Requires-Dist: numpy
Requires-Dist: requests
